{
  "info": {
    "colName": "attr_13",
    "type": "Numeric",
    "index": "13"
  },
  "points": [
    {
      "x1": "-2.091759904E9",
      "x2": "-1.6771676968E9",
      "y": "9"
    },
    {
      "x1": "-1.6771676968E9",
      "x2": "-1.2625754896E9",
      "y": "125"
    },
    {
      "x1": "-1.2625754896E9",
      "x2": "-8.479832823999999E8",
      "y": "42"
    },
    {
      "x1": "-8.479832823999999E8",
      "x2": "-4.3339107519999987E8",
      "y": "116"
    },
    {
      "x1": "-4.3339107519999987E8",
      "x2": "-1.879886799999988E7",
      "y": "65"
    },
    {
      "x1": "-1.879886799999988E7",
      "x2": "3.957933392000001E8",
      "y": "490"
    },
    {
      "x1": "3.957933392000001E8",
      "x2": "8.103855464000001E8",
      "y": "363"
    },
    {
      "x1": "8.103855464000001E8",
      "x2": "1.2249777536000001E9",
      "y": "246"
    },
    {
      "x1": "1.2249777536000001E9",
      "x2": "1.6395699608000002E9",
      "y": "69"
    },
    {
      "x1": "1.6395699608000002E9",
      "x2": "2.054162168E9",
      "y": "14639"
    }
  ],
  "viewType": "Graph"
}